Metadata-Version: 2.1
Name: shellfoundry
Version: 1.2.27
Summary: shellfoundry - Quali tool for creating, building and installing CloudShell shells
Home-page: https://github.com/QualiSystems/shellfoundry
Author: Quali
Author-email: info@quali.com
License: Apache Software License 2.0
Keywords: shellfoundry sandbox cloud virtualization vcenter cmp cloudshell quali command-line cli
Classifier: Development Status :: 5 - Production/Stable
Classifier: Programming Language :: Python :: 2.7
Classifier: Programming Language :: Python :: 3.7
Classifier: Topic :: Software Development :: Libraries
Classifier: License :: OSI Approved :: Apache Software License
Requires-Python: >=2.7
License-File: LICENSE
Requires-Dist: requests
Requires-Dist: cookiecutter ~=1.7.2
Requires-Dist: click ~=7.1.2
Requires-Dist: pyyaml
Requires-Dist: terminaltables
Requires-Dist: cloudshell-rest-api ~=9.0.0
Requires-Dist: colorama
Requires-Dist: giturlparse.py
Requires-Dist: ruamel.yaml
Requires-Dist: cryptography
Requires-Dist: setuptools ; python_version >= "3.12"
